<?xml version="1.0" encoding="UTF-8"?>
<metadata xml:lang="ar"><Esri><CreaDate>20220328</CreaDate><CreaTime>18080300</CreaTime><ArcGISFormat>1.0</ArcGISFormat><SyncOnce>TRUE</SyncOnce><DataProperties><itemProps><itemLocation><linkage Sync="TRUE">file://\\COMPUTERMARKET\D$\Elhamady\Arc_GIS\Project\New folder\M_roads</linkage><protocol Sync="TRUE">Local Area Network</protocol></itemLocation></itemProps><copyHistory><copy source="D:\Elhamady\Arc_GIS\Q_Gis\M_roads" dest="\\COMPUTERMARKET\D$\Elhamady\Arc_GIS\Project\New folder\M_roads" date="20220328" time="18080300"></copy></copyHistory></DataProperties></Esri></metadata>
